orm_loader/__init__.py
orm_loader/helpers/__init__.py
orm_loader/helpers/bootstrap.py
orm_loader/helpers/bulk.py
orm_loader/helpers/discovery.py
orm_loader/helpers/errors.py
orm_loader/helpers/logging.py
orm_loader/helpers/metadata.py
orm_loader/helpers/sqlite.py
orm_loader/loaders/__init__.py
orm_loader/loaders/data/__init__.py
orm_loader/loaders/data/converters.py
orm_loader/loaders/data_classes.py
orm_loader/loaders/loader_interface.py
orm_loader/loaders/loading_helpers.py
orm_loader/mappers/__init__.py
orm_loader/mappers/materialised_view_mixin.py
orm_loader/py.typed
orm_loader/registry/__init__.py
orm_loader/registry/registry.py
orm_loader/registry/validation.py
orm_loader/registry/validation_presets.py
orm_loader/registry/validation_report.py
orm_loader/registry/validation_runner.py
orm_loader/tables/__init__.py
orm_loader/tables/allocators.py
orm_loader/tables/loadable_table.py
orm_loader/tables/orm_table.py
orm_loader/tables/serialisable_table.py
orm_loader/tables/typing.py
orm_loader-0.3.11.dist-info/WHEEL
orm_loader-0.3.11.dist-info/METADATA
orm_loader-0.3.11.dist-info/RECORD
