Metadata-Version: 2.3
Name: orm-loader
Version: 0.3.11
Summary: Generic base classes to handle ORM functionality for multiple downstream datamodels
Author: gkennos
Author-email: gkennos <georgina.kennedy@unsw.edu.au>
Requires-Dist: chardet>=5.2.0
Requires-Dist: pandas>=2.3.3
Requires-Dist: pyarrow>=23.0.0
Requires-Dist: sqlalchemy>=2.0.45
Requires-Dist: mypy>=1.19.1 ; extra == 'dev'
Requires-Dist: pytest>=9.0.2 ; extra == 'dev'
Requires-Dist: ruff>=0.14.11 ; extra == 'dev'
Requires-Dist: mkdocs-material>=9.7.1 ; extra == 'dev'
Requires-Dist: mkdocstrings-python>=2.0.1 ; extra == 'dev'
Requires-Dist: mkdocs>=1.6.1 ; extra == 'dev'
Requires-Dist: mkdocs-mermaid2-plugin ; extra == 'dev'
Requires-Python: >=3.12
Project-URL: Homepage, https://AustralianCancerDataNetwork.github.io/orm-loader
Project-URL: Documentation, https://AustralianCancerDataNetwork.github.io/orm-loader
Project-URL: Repository, https://github.com/AustralianCancerDataNetwork/orm-loader
Project-URL: Issues, https://github.com/AustralianCancerDataNetwork/orm-loader/issues
Provides-Extra: dev
